codezap_mcp/__init__.py
codezap_mcp/__main__.py
codezap_mcp/docs.py
codezap_mcp/prd.py
codezap_mcp/server.py
codezap_mcp/utils/callback_server.py
codezap_mcp/utils/platform_utils.py
codezap_mcp/utils/static/placeholder.txt
codezap_mcp/utils/templates/survey_template.html
codezap_mcp-0.1.3.dist-info/METADATA
codezap_mcp-0.1.3.dist-info/WHEEL
codezap_mcp-0.1.3.dist-info/entry_points.txt
codezap_mcp-0.1.3.dist-info/top_level.txt
codezap_mcp-0.1.3.dist-info/RECORD
