Metadata-Version: 2.4
Name: codezap-mcp
Version: 0.1.3
Summary: ⚡️ The MCP Server designed to guide Vibe Coder's development.
Requires-Python: >=3.10
Requires-Dist: mcp[cli]>=1.8.1
Requires-Dist: requests>=2.32.3
